{"book_num":{"0":1,"1":2,"2":3,"3":4,"4":5,"5":6,"6":7,"7":8,"8":9,"9":10,"10":11,"11":12,"12":13,"13":14,"14":15,"15":16,"16":17,"17":18,"18":19,"19":20,"20":21,"21":22,"22":23,"23":24,"24":25,"25":26,"26":27,"27":28,"28":29,"29":30,"30":31,"31":32,"32":33,"33":34,"34":35,"35":36,"36":37,"37":38,"38":39,"39":40,"40":41,"41":42,"42":43,"43":44,"44":45,"45":46,"46":47,"47":48,"48":49,"49":50,"50":51,"51":52,"52":53,"53":54,"54":55,"55":56,"56":57,"57":58,"58":59,"59":60,"60":61,"61":62,"62":63,"63":64,"64":65,"65":66,"66":67,"67":68,"68":69,"69":70,"70":71,"71":72,"72":73,"73":74,"74":75,"75":76,"76":77,"77":78,"78":79,"79":80,"80":81,"81":82,"82":83,"83":84,"84":85,"85":86,"86":87,"87":88,"88":89,"89":90,"90":91,"91":92,"92":93,"93":94,"94":95,"95":96,"96":97,"97":98,"98":99,"99":100},"book_name":{"0":"Astrophysics for People in a Hurry Book by Neil deGrasse Tyson","1":"Physics of the Impossible: A Scientific Exploration into the World of Phasers Force Fields Teleportation and Time Travel Book by Michio Kaku","2":"Pale Blue Dot: A Vision of the Human Future in Space Book by Carl Sagan","3":"Brief Answers to the Big Questions Book by Stephen Hawking","4":"My Brief History Book by Stephen Hawking","5":"A Universe from Nothing Book by Lawrence M Krauss","6":"The God Delusion Book by Richard Dawkins","7":"Just Six Numbers Book by Martin Rees","8":"The Republic Book by Plato","9":"Life 3.0: Being Human in the Age of Artificial Intelligence Book by Max Tegmark","10":"Rich Dad Poor Dad Book by Robert Kiyosaki and Sharon Lechter","11":"Talking to my daughter about the economy Book by Yanis Varoufakis","12":"The Science of Interstellar Book by Kip Thorne","13":"The Universe in a Nutshell Book by Stephen Hawking","14":"The Art of War Book by Sunzi","15":"Sapiens: A Brief History of Humankind Book by Yuval Noah Harari","16":"The Ascent of Money: A Financial History of the World Book by Niall Ferguson","17":"The Demon-Haunted World Book by Ann Druyan and Carl Sagan","18":"Superintelligence: Paths Dangers Strategies Book by Nick Bostrom","19":"Homo Deus Book by Yuval Noah Harari","20":"21 Lessons for the 21st Century Book by Yuval Noah Harari","21":"Man's Search for Meaning Book by Viktor Frankl","22":"Nineteen Eighty-Four Novel by George Orwell","23":"Accessory to War Book by Neil deGrasse Tyson","24":"Factfulness: Ten Reasons We're Wrong About the World--and Why Things Are Better Than You Think Book by Anna Rosling R\u00f6nnlund Hans Rosling and Ola Rosling","25":"What If?: Serious Scientific Answers to Absurd Hypothetical Questions Book by Randall Munroe","26":"Brave New World (New Longman Literature) Novel by Aldous Huxley","27":"Never Split the Difference: Negotiating As If Your Life Depended On It Book by Christopher Voss and Tahl Raz","28":"The Idiot Brain: A Neuroscientist Explains What Your Head Is Really Up To Book by Dean Burnett","29":"Think and Grow Rich Book by Napoleon Hill","30":"Flatland Book by Edwin Abbott Abbott","31":"Outliers Book by Malcolm Gladwell","32":"The Science of Fate: The New Science of Who We Are - And How to Shape Our Best Future Book by Hannah Critchlow","33":"Contact Novel by Carl Sagan","34":"The Order of Time Book by Carlo Rovelli","35":"Do Dice Play God? The Mathematics of Uncertainty Book by Ian Stewart","36":"David and Goliath Book by Malcolm Gladwell","37":"The Tipping Point: How Little Things Can Make a Big Difference Book by Malcolm Gladwell","38":"Influence: Science and Practice Book by Robert Cialdini","39":"Quiet: The Power of Introverts in a World That Can't Stop Talking Book by Susan Cain","40":"The Trial Novel by Franz Kafka","41":"Animal Farm Book by George Orwell","42":"Blink: The Power of Thinking Without Thinking Book by Malcolm Gladwell","43":"The Case Against Reality: How Evolution Hid the Truth from Our Eyes Book by Donald D Hoffman","44":"The Great Influenza Book by John M Barry","45":"Maps of Meaning Book by Jordan Peterson","46":"Talking to Strangers Book by Malcolm Gladwell","47":"The Happiness Equation: Want Nothing + Do Anything Book by Neil Pasricha","48":"Zero to One Book by Blake Masters and Peter Thiel","49":"The 4-Hour Workweek Book by Tim Ferriss","50":"An Autobiography: The story of My Experiments with Truth Book by Mahatma Gandhi","51":"Nightfall by Isaac Asimov  (Author) Robert Silverberg (Author)","52":"Ikigai: The Japanese Secret to a Long and Happy Life Book by Albert Liebermann and Hector Garcia","53":"Midnight in Chernobyl Book by Adam Higginbotham","54":"The Road to Wigan Pier Book by George Orwell","55":"Anthem Book by Ayn Rand","56":"Lord of the Flies Novel by William Golding","57":"A Brief History of Time Book by Stephen Hawking","58":"One Up on Wall Street Book by John Rothchild and Peter Lynch","59":"Chaos: Making a New Science Book by James Gleick","60":"The Giver Novel by Lois Lowry","61":"Fahrenheit 451 Novel by Ray Bradbury","62":"Making Habits Breaking Habits: Why We Do Things Why We Don't and How to Make Any Change Stick Book by Jeremy Dean","63":"The Selfish Gene Book by Richard Dawkins","64":"How to Avoid a Climate Disaster: The Solutions We Have and the Breakthroughs We Need Book by Bill Gates","65":"The Gulag Archipelago Book by Aleksandr Solzhenitsyn","66":"Where Good Ideas Come from: The Natural History of Innovation Book by Steven Johnson","67":"Foundation Novel by Isaac Asimov","68":"Foundation and Empire Novel by Isaac Asimov","69":"Ordinary Men: Reserve Police Battalion 101 and the Final Solution in Poland Book by Christopher Browning","70":"Permanent Record Book by Edward Snowden","71":"The Demon in the Freezer: A True Story Book by Richard Preston","72":"On Intelligence Book by Jeff Hawkins and Sandra Blakeslee","73":"The Bomber Mafia Book by Malcolm Gladwell","74":"Second Foundation Novel by Isaac Asimov","75":"Born a Crime Book by Trevor Noah","76":"The Ride of a Lifetime Book by Robert Iger","77":"The Black Cloud Novel by Colin Swatridge and Fred Hoyle","78":"Brief Interviews with Hideous Men Book by David Foster Wallace","79":"In Order to Live Book by Maryanne Vollers and Park Yeon-mi","80":"The Missionary Position: Mother Teresa in Theory and Practice Book by Christopher Hitchens","81":"Fast Feast Repeat: The Comprehensive Guide to Delay Don't Deny Intermittent Fasting--Including the 28-Day FAST Start Book by Gin Stephens","82":"Dear Reader: The Unauthorized Autobiography of Kim Jong Il Book by Michael Malice","83":"The New Right: A Journey to the Fringe of American Politics Book by Michael Malice","84":"Solaris Novel by Stanis\u0142aw Lem","85":"Lifespan: Why We Age \u2013 and Why We Don't Have To Book by David Sinclair","86":"I Am Legend Novel by Richard Matheson","87":"We Novel by Yevgeny Zamyatin","88":"The Metamorphosis Novella by Franz Kafka","89":"Inglorious Empire Book by Shashi Tharoor","90":"Energy and Civilization: A History Book by Professor of Geography Vaclav Smil","91":"Never Let Me Go Novel by Kazuo Ishiguro","92":"The Stranger Book by Albert Camus","93":"The Children of Men Novel by P D James","94":"Start With Why Book by Simon Sinek","95":"Find Your Why: A Practical Guide for Discovering Purpose for You and Your Team Book by David Mead Peter Docker and Simon Sinek","96":"Bad Science Book by Ben Goldacre","97":"Bad Blood: Secrets and Lies in a Silicon Valley Startup Book by John Carreyrou","98":"Billion Dollar Loser: The Epic Rise and Fall of WeWork Book by Reeves Wiedeman","99":"The Road to Jonestown: Jim Jones and Peoples Temple Book by Jeff Guinn"},"book_url":{"0":"https:\/\/www.goodreads.com\/book\/show\/32191710-astrophysics-for-people-in-a-hurry","1":"https:\/\/www.goodreads.com\/book\/show\/1168341.Physics_of_the_Impossible","2":"https:\/\/www.goodreads.com\/book\/show\/61663.Pale_Blue_Dot","3":"https:\/\/www.goodreads.com\/book\/show\/40277241-brief-answers-to-the-big-questions","4":"https:\/\/www.goodreads.com\/book\/show\/18209305-my-brief-history","5":"https:\/\/www.goodreads.com\/book\/show\/11337189-a-universe-from-nothing","6":"https:\/\/www.goodreads.com\/book\/show\/14743.The_God_Delusion","7":"https:\/\/www.goodreads.com\/book\/show\/81884.Just_Six_Numbers","8":"https:\/\/www.goodreads.com\/book\/show\/30289.The_Republic","9":"https:\/\/www.goodreads.com\/book\/show\/34272565-life-3-0","10":"https:\/\/www.goodreads.com\/book\/show\/69571.Rich_Dad_Poor_Dad","11":"https:\/\/www.goodreads.com\/book\/show\/36490332-talking-to-my-daughter-about-the-economy","12":"https:\/\/www.goodreads.com\/book\/show\/23261448-the-science-of-interstellar","13":"https:\/\/www.goodreads.com\/book\/show\/2095.The_Universe_in_a_Nutshell","14":"https:\/\/www.goodreads.com\/book\/show\/10534.The_Art_of_War","15":"https:\/\/www.goodreads.com\/book\/show\/23692271-sapiens","16":"https:\/\/www.goodreads.com\/book\/show\/2714607-the-ascent-of-money","17":"https:\/\/www.goodreads.com\/book\/show\/17349.The_Demon_Haunted_World","18":"https:\/\/www.goodreads.com\/book\/show\/20527133-superintelligence","19":"https:\/\/www.goodreads.com\/book\/show\/31138556-homo-deus","20":"https:\/\/www.goodreads.com\/book\/show\/38820046-21-lessons-for-the-21st-century","21":"https:\/\/www.goodreads.com\/book\/show\/4069.Man_s_Search_for_Meaning","22":"https:\/\/www.goodreads.com\/book\/show\/40961427-1984","23":"https:\/\/www.goodreads.com\/book\/show\/44157732-accessory-to-war","24":"https:\/\/www.goodreads.com\/book\/show\/34890015-factfulness","25":"https:\/\/www.goodreads.com\/book\/show\/21413662-what-if-serious-scientific-answers-to-absurd-hypothetical-questions","26":"https:\/\/www.goodreads.com\/book\/show\/5129.Brave_New_World","27":"https:\/\/www.goodreads.com\/book\/show\/26156469-never-split-the-difference","28":"https:\/\/www.goodreads.com\/book\/show\/32191721-idiot-brain","29":"https:\/\/www.goodreads.com\/book\/show\/30186948-think-and-grow-rich","30":"https:\/\/www.goodreads.com\/book\/show\/433567.Flatland","31":"https:\/\/www.goodreads.com\/book\/show\/3228917-outliers","32":"https:\/\/www.goodreads.com\/en\/book\/show\/45159747-the-science-of-fate","33":"https:\/\/www.goodreads.com\/book\/show\/61666.Contact","34":"https:\/\/www.goodreads.com\/book\/show\/36442813-the-order-of-time","35":"https:\/\/www.goodreads.com\/book\/show\/43522601-do-dice-play-god","36":"https:\/\/www.goodreads.com\/book\/show\/15751404-david-and-goliath","37":"https:\/\/www.goodreads.com\/book\/show\/2612.The_Tipping_Point","38":"https:\/\/www.goodreads.com\/book\/show\/28815.Influence","39":"https:\/\/www.goodreads.com\/book\/show\/8520610-quiet","40":"https:\/\/www.goodreads.com\/book\/show\/17690.The_Trial","41":"https:\/\/www.goodreads.com\/book\/show\/170448.Animal_Farm","42":"https:\/\/www.goodreads.com\/book\/show\/40102.Blink","43":"https:\/\/www.goodreads.com\/en\/book\/show\/41817484-the-case-against-reality","44":"https:\/\/www.goodreads.com\/book\/show\/29036.The_Great_Influenza","45":"https:\/\/www.goodreads.com\/book\/show\/2218102.Maps_of_Meaning","46":"https:\/\/www.goodreads.com\/book\/show\/43848929-talking-to-strangers","47":"https:\/\/www.goodreads.com\/book\/show\/22571656-the-happiness-equation","48":"https:\/\/www.goodreads.com\/book\/show\/18050143-zero-to-one","49":"https:\/\/www.goodreads.com\/book\/show\/368593.The_4_Hour_Workweek","50":"https:\/\/www.goodreads.com\/book\/show\/112803.Gandhi","51":"https:\/\/www.goodreads.com\/book\/show\/99245.Nightfall","52":"https:\/\/www.goodreads.com\/book\/show\/40534545-ikigai","53":"https:\/\/www.goodreads.com\/book\/show\/40538681-midnight-in-chernobyl","54":"https:\/\/www.goodreads.com\/book\/show\/30553.The_Road_to_Wigan_Pier","55":"https:\/\/www.goodreads.com\/book\/show\/667.Anthem","56":"https:\/\/www.goodreads.com\/book\/show\/7624.Lord_of_the_Flies","57":"https:\/\/www.goodreads.com\/book\/show\/3869.A_Brief_History_of_Time","58":"https:\/\/www.goodreads.com\/book\/show\/762462.One_Up_On_Wall_Street","59":"https:\/\/www.goodreads.com\/book\/show\/64582.Chaos","60":"https:\/\/www.goodreads.com\/book\/show\/3636.The_Giver","61":"https:\/\/www.goodreads.com\/book\/show\/13079982-fahrenheit-451","62":"https:\/\/www.goodreads.com\/book\/show\/13587213-making-habits-breaking-habits","63":"https:\/\/www.goodreads.com\/book\/show\/61535.The_Selfish_Gene","64":"https:\/\/www.goodreads.com\/book\/show\/52275335-how-to-avoid-a-climate-disaster","65":"https:\/\/www.goodreads.com\/book\/show\/70561.The_Gulag_Archipelago_1918_1956","66":"https:\/\/www.goodreads.com\/book\/show\/8034188-where-good-ideas-come-from","67":"https:\/\/www.goodreads.com\/book\/show\/29579.Foundation","68":"https:\/\/www.goodreads.com\/book\/show\/29581.Foundation_and_Empire","69":"https:\/\/www.goodreads.com\/book\/show\/647492.Ordinary_Men","70":"https:\/\/www.goodreads.com\/book\/show\/46223297-permanent-record","71":"https:\/\/www.goodreads.com\/book\/show\/198505.The_Demon_in_the_Freezer","72":"https:\/\/www.goodreads.com\/book\/show\/27539.On_Intelligence","73":"https:\/\/www.goodreads.com\/book\/show\/56668328-the-bomber-mafia","74":"https:\/\/www.goodreads.com\/book\/show\/29580.Second_Foundation","75":"https:\/\/www.goodreads.com\/book\/show\/29780253-born-a-crime","76":"https:\/\/www.goodreads.com\/book\/show\/44525305-the-ride-of-a-lifetime","77":"https:\/\/www.goodreads.com\/book\/show\/1246118.The_Black_Cloud","78":"https:\/\/www.goodreads.com\/book\/show\/6753.Brief_Interviews_with_Hideous_Men","79":"https:\/\/www.goodreads.com\/book\/show\/24611623-in-order-to-live","80":"https:\/\/www.goodreads.com\/book\/show\/43372.The_Missionary_Position","81":" https:\/\/www.goodreads.com\/book\/show\/51168294-fast-feast-repeat","82":"https:\/\/www.goodreads.com\/en\/book\/show\/20652901-dear-reader","83":"https:\/\/www.goodreads.com\/book\/show\/34964949-the-new-right","84":"https:\/\/www.goodreads.com\/book\/show\/95558.Solaris","85":"https:\/\/www.goodreads.com\/book\/show\/43723901-lifespan","86":"https:\/\/www.goodreads.com\/book\/show\/40940649-i-am-legend","87":"https:\/\/www.goodreads.com\/book\/show\/76171.We","88":"https:\/\/www.goodreads.com\/book\/show\/485894.The_Metamorphosis","89":"https:\/\/www.goodreads.com\/book\/show\/34185892-inglorious-empire","90":"https:\/\/www.goodreads.com\/book\/show\/31850765-energy-and-civilization","91":"https:\/\/www.goodreads.com\/book\/show\/6334.Never_Let_Me_Go","92":"https:\/\/www.goodreads.com\/book\/show\/49552.The_Stranger","93":"https:\/\/www.goodreads.com\/book\/show\/41913.The_Children_of_Men","94":"https:\/\/www.goodreads.com\/book\/show\/7108725-start-with-why","95":"https:\/\/www.goodreads.com\/book\/show\/29496432-find-your-why","96":"https:\/\/www.goodreads.com\/book\/show\/3272165-bad-science","97":"https:\/\/www.goodreads.com\/book\/show\/37976541-bad-blood","98":"https:\/\/www.goodreads.com\/book\/show\/54502643-billion-dollar-loser","99":"https:\/\/www.goodreads.com\/book\/show\/40726412-the-road-to-jonestown"},"genres":{"0":"Science, Audiobook, Space, Education, Nonfiction, History, Adult","1":"Science, Audiobook, Space, Reference, Nonfiction, Science Fiction","2":"Science, Philosophy, Audiobook, Space, Nonfiction, History","3":"Science, Philosophy, Audiobook, Space, Writing, Nonfiction, Adult","4":"Science, Biography Memoir, Biography, Audiobook, Nonfiction, Autobiography, History","5":"Science, Philosophy, Audiobook, Space, Nonfiction, Religion","6":"Science, Philosophy, Psychology, Audiobook, Spirituality, Nonfiction, Religion, Biology","7":"Science, Philosophy, Science Nature, Space, Nonfiction, History","8":"Philosophy, Academic, Politics, Literature, Nonfiction, History, Classics","9":"Science, Philosophy, Audiobook, Business, Futurism, Nonfiction, Artificial Intelligence","10":"Audiobook, Self Help, Finance, Business, Currency, Nonfiction, Economics","11":"Philosophy, Audiobook, Sociology, Cultural, Business, Politics, Nonfiction, History, Economics","12":"Science, Audiobook, Unfinished, Space, Nonfiction, Culture, Science Fiction","13":"Science, Philosophy, Audiobook, Space, Education, Nonfiction, History","14":"Philosophy, War, Leadership, Cultural, Business, Politics, Nonfiction, History, Classics","15":"Historical, Philosophy, Science, Psychology, Audiobook, Sociology, Anthropology, Nonfiction, History, Biology","16":"Historical, Audiobook, Business, Politics, Currency, Nonfiction, History, Economics","17":"Science, Philosophy, Psychology, Nonfiction, Religion, History","18":"Science, Psychology, Philosophy, Unfinished, Business, Futurism, Nonfiction, Artificial Intelligence","19":"Philosophy, Science, Psychology, Audiobook, Sociology, Anthropology, Politics, Nonfiction, History","20":"Philosophy, Science, Psychology, Audiobook, Sociology, Self Help, Politics, Nonfiction, Culture, History","21":"Philosophy, Psychology, Biography, Self Help, Spirituality, Nonfiction, World War II, Autobiography, History, Classics","22":"Academic, Novels, Fiction, Politics, Literature, Adult, Science Fiction, Classics, Fantasy","23":"Science, War, Audiobook, Space, Politics, Nonfiction, History","24":"Science, Psychology, Philosophy, Self Help, Sociology, Business, Politics, Nonfiction, History, Economics","25":"Science, Audiobook, Reference, Nonfiction, Humor, Sequential Art, Adult","26":"Philosophy, Academic, Novels, Fiction, Literature, Science Fiction, Classics, Science Fiction Fantasy, Fantasy","27":"Leadership, Psychology, Language, Audiobook, Self Help, Business, Nonfiction","28":"Science, Psychology, Audiobook, Neuroscience, Self Help, Nonfiction, Health, Biology","29":"Philosophy, Psychology, Audiobook, Self Help, Finance, Business, Currency, Nonfiction, Classics, Economics","30":"Science, Philosophy, Novels, Fiction, Literature, Science Fiction, Classics, Fantasy","31":"Science, Psychology, Leadership, Audiobook, Self Help, Sociology, Business, Nonfiction, Economics","32":"Science, Psychology, Audiobook, Sociology, Nonfiction, Biology","33":"Audiobook, Space, Novels, Fiction, Speculative Fiction, Science Fiction, Classics, Science Fiction Fantasy, Fantasy","34":"Science, Philosophy, Audiobook, Writing, Cultural, Nonfiction, History, European Literature","35":"Science, Nonfiction, Philosophy, Audiobook","36":"Science, Psychology, Leadership, Audiobook, Self Help, Sociology, Business, Nonfiction, History","37":"Science, Psychology, Leadership, Audiobook, Philosophy, Sociology, Self Help, Business, Nonfiction, Economics","38":"Leadership, Psychology, Science, Language, Self Help, Business, Nonfiction, Buisness","39":"Science, Psychology, Leadership, Audiobook, Self Help, Sociology, Business, Nonfiction, Adult","40":"Philosophy, Novels, Fiction, Literature, Science Fiction, Literary Fiction, European Literature, Classics","41":"Academic, Novels, Fiction, Politics, Literature, Science Fiction, Classics, Fantasy","42":"Science, Psychology, Philosophy, Audiobook, Leadership, Self Help, Sociology, Business, Nonfiction","43":"Science, Psychology, Philosophy, Audiobook, Nonfiction, History, Biology","44":"Historical, Science, Audiobook, Medical, Nonfiction, Health, History, North American Hi...","45":"Philosophy, Psychology, Science, Audiobook, Self Help, Politics, Nonfiction, Religion, History, Fantasy","46":"Science, Psychology, Language, Audiobook, Self Help, Sociology, Business, Nonfiction, Adult","47":"Philosophy, Psychology, Inspirational, Audiobook, Self Help, Business, Nonfiction, Health, Productivity","48":"Science, Leadership, Self Help, Business, Nonfiction, Buisness, Economics","49":"Psychology, Audiobook, Self Help, Business, Nonfiction, Buisness, Productivity, Economics","50":"Philosophy, Biography Memoir, Biography, Cultural, Politics, Spirituality, Nonfiction, Autobiography, History","51":"Speculative Fiction, Fiction, Short Stories, Novels, Literature, Apocalyptic, Science Fiction, Classics, Science Fiction Fantasy, Fantasy","52":"Philosophy, Psychology, Audiobook, Self Help, Cultural, Spirituality, Nonfiction, Health, Productivity","53":"Historical, Science, Audiobook, Cultural, Politics, Nonfiction, History, Environment","54":"Biography, Writing, Sociology, Politics, Literature, Nonfiction, History, European Literature, Classics, Economics","55":"Philosophy, Academic, Novels, Fiction, Politics, Literature, Science Fiction, Classics","56":"Academic, Novels, Fiction, Literature, Science Fiction, Young Adult, Classics, Adventure","57":"Science, Philosophy, Audiobook, Space, Nonfiction, History, Classics","58":"Audiobook, Biography, Self Help, Finance, Business, Currency, Nonfiction, Buisness, Economics","59":"Science, Philosophy, Psychology, Audiobook, Unfinished, Nonfiction, History","60":"Academic, Fiction, Childrens, Young Adult, Science Fiction, Classics, Fantasy","61":"Audiobook, Academic, Novels, Fiction, Literature, Adult, Science Fiction, Classics, Fantasy","62":"Science, Psychology, Leadership, Audiobook, Self Help, Business, Nonfiction, Health, Productivity","63":"Science, Psychology, Philosophy, Audiobook, Nonfiction, Religion, Biology","64":"Science, Audiobook, Business, Politics, Nonfiction, Environment, Economics","65":"Historical, Biography, Cultural, Politics, Literature, Nonfiction, Autobiography, History, Classics","66":"Science, Psychology, Philosophy, Self Help, Business, Design, Nonfiction, History","67":"Audiobook, Space, Novels, Fiction, Speculative Fiction, Science Fiction, Classics, Science Fiction Fantasy, Fantasy","68":"Audiobook, Space, Novels, Fiction, Speculative Fiction, Science Fiction, Classics, Science Fiction Fantasy, Fantasy","69":"Historical, Psychology, War, Cultural, Politics, Nonfiction, World War II, History","70":"Science, Biography Memoir, Biography, Audiobook, Politics, Nonfiction, Autobiography, History","71":"Thriller, Science, Audiobook, Medical, Nonfiction, Health, Illness, History","72":"Science, Psychology, Philosophy, Neuroscience, Nonfiction, Artificial Intelligence, Biology","73":"Historical, War, Aviation, Audiobook, Nonfiction, Military, History, North American Hi...","74":"Audiobook, Space, Novels, Fiction, Speculative Fiction, Science Fiction, Classics, Science Fiction Fantasy, Fantasy","75":"Biography Memoir, Biography, Audiobook, Cultural, Southern Africa, Nonfiction, Humor, Autobiography, Race","76":"Leadership, Biography Memoir, Biography, Audiobook, Self Help, Business, Nonfiction, Autobiography","77":"Novels, Fiction, Speculative Fiction, European Literature, Literature, Science Fiction, Classics, Science Fiction Fantasy, Fantasy","78":"Audiobook, Unfinished, Writing, Fiction, Short Stories, Literature, Humor, Literary Fiction, Contemporary","79":"Biography Memoir, Biography, Audiobook, Cultural, Politics, Nonfiction, Autobiography, History, Adult","80":"Philosophy, Biography, Writing, Cultural, Politics, Nonfiction, Religion, History","81":"Audiobook, Adult, Self Help, Sports, Nonfiction, Health, Food and Drink","82":"Biography, Audiobook, Unfinished, Cultural, Politics, Nonfiction, Humor, History","83":"Philosophy, Audiobook, Sociology, Cultural, Politics, Literature, Nonfiction, Culture, History","84":"Philosophy, Audiobook, Cultural, Novels, Fiction, European Literature, Science Fiction, Classics, Science Fiction Fantasy, Fantasy","85":"Science, Psychology, Audiobook, Medical, Self Help, Nonfiction, Health","86":"Audiobook, Paranormal, Horror, Fiction, Apocalyptic, Science Fiction, Classics, Fantasy","87":"Cultural, Novels, Fiction, Literature, Science Fiction, Classics, Science Fiction Fantasy","88":"Philosophy, Horror, Academic, Novels, Fiction, Short Stories, Literature, European Literature, Classics, Fantasy","89":"Historical, Audiobook, Cultural, Politics, Asian Literature, Nonfiction, History, Race, Economics","90":"Science, Business, Politics, Nonfiction, History, Environment, Economics","91":"Novels, Fiction, Romance, Literature, European Literature, Literary Fiction, Adult, Science Fiction, Contemporary","92":"Philosophy, Cultural, Academic, Novels, Fiction, Literature, Literary Fiction, European Literature, Classics","93":"Thriller, Speculative Fiction, Novels, Apocalyptic, Mystery, Science Fiction, Fiction, Science Fiction Fantasy, Fantasy","94":"Leadership, Psychology, Audiobook, Self Help, Business, Nonfiction, Buisness","95":"Leadership, Psychology, Philosophy, Audiobook, Self Help, Business, Nonfiction, Buisness","96":"Science, Psychology, Philosophy, Audiobook, Medical, Nonfiction, Health, Humor","97":"Science, Audiobook, Biography, Writing, Business, Crime, Nonfiction, History, Mystery","98":"Science, Biography Memoir, Biography, Audiobook, Business, Nonfiction, History, Economics","99":"Historical, Psychology, Biography, Audiobook, Crime, Nonfiction, Religion, History, Mystery"}}